{"algebra_data" : "IsPathAlgebra\nVertices:\n1, 2, 3\nArrows:\na_1:1->2, a_2:3->2\nField:\nRationals\n","indecomposables" : [{"dim_vector" : [1,1,0],"id" : 0,"inj_dim" : 1,"orbit" : 1,"orbit_position" : 0,"proj_dim" : 0,"tau_rigidity_row" : [1,0,1,1,1,1]},{"dim_vector" : [0,0,1],"id" : 1,"inj_dim" : 0,"orbit" : 1,"orbit_position" : 1,"proj_dim" : 1,"tau_rigidity_row" : [1,1,1,1,1,1]},{"dim_vector" : [0,1,0],"id" : 2,"inj_dim" : 1,"orbit" : 2,"orbit_position" : 0,"proj_dim" : 0,"tau_rigidity_row" : [1,0,1,0,1,0]},{"dim_vector" : [1,1,1],"id" : 3,"inj_dim" : 0,"orbit" : 2,"orbit_position" : 1,"proj_dim" : 1,"tau_rigidity_row" : [1,1,1,1,1,1]},{"dim_vector" : [0,1,1],"id" : 4,"inj_dim" : 1,"orbit" : 3,"orbit_position" : 0,"proj_dim" : 0,"tau_rigidity_row" : [1,1,1,1,1,0]},{"dim_vector" : [1,0,0],"id" : 5,"inj_dim" : 0,"orbit" : 3,"orbit_position" : 1,"proj_dim" : 1,"tau_rigidity_row" : [1,1,1,1,1,1]}],"number_arrows" : 2,"number_modules" : 6,"number_orbits" : 3,"number_vertices" : 3}